reflex_animated_cursor/__init__.py
reflex_animated_cursor/animated_cursor.py
reflex_animated_cursor-0.0.1.dist-info/METADATA
reflex_animated_cursor-0.0.1.dist-info/WHEEL
reflex_animated_cursor-0.0.1.dist-info/top_level.txt
reflex_animated_cursor-0.0.1.dist-info/RECORD
