Metadata-Version: 2.1
Name: reflex-animated-cursor
Version: 0.0.1
Summary: Reflex custom component animated-cursor
Author-email: Adarsh Gourab Mahalik <gourabmahalikadarsh@gmail.com>
License: Apache-2.0
Keywords: reflex,reflex-custom-components
Classifier: Development Status :: 4 - Beta
Requires-Python: >=3.8
Requires-Dist: reflex >=0.4.2
Provides-Extra: dev
Requires-Dist: build ; extra == 'dev'
Requires-Dist: twine ; extra == 'dev'
